{
  "name": "Forgejo",
  "logo": "https://codeberg.org/forgejo/governance/raw/branch/main/branding/logo/forgejo.svg",
  "description": "Self-hosted lightweight software forge — Git hosting, issues, and pull requests",
  "categories": ["development"],
  "images": [],
  "configurations": [
    {
      "title": "SMTP",
      "schema": { "properties": {} },
      "default_value": {},
      "destinations": [
        { "type": "smtp", "container": "forgejo", "key": "FORGEJO__mailer__ENABLED" },
        { "type": "smtp", "container": "forgejo", "key": "FORGEJO__mailer__SMTP_ADDR" },
        { "type": "smtp", "container": "forgejo", "key": "FORGEJO__mailer__SMTP_PORT" },
        { "type": "smtp", "container": "forgejo", "key": "FORGEJO__mailer__USER" },
        { "type": "smtp", "container": "forgejo", "key": "FORGEJO__mailer__PASSWD" },
        { "type": "smtp", "container": "forgejo", "key": "FORGEJO__mailer__FROM" },
        { "type": "smtp", "container": "forgejo", "key": "FORGEJO__mailer__PROTOCOL" }
      ]
    }
  ]
}
